LICENSE
MANIFEST.in
README.rst
setup.cfg
setup.py
django_generator/__init__.py
django_generator/form_make.py
django_generator/utils.py
django_generator/view_make.py
django_generator.egg-info/PKG-INFO
django_generator.egg-info/SOURCES.txt
django_generator.egg-info/dependency_links.txt
django_generator.egg-info/top_level.txt
django_generator/management/__init__.py
django_generator/management/commands/__init__.py
django_generator/management/commands/app_template.tar.gz
django_generator/management/commands/generate_app.py
django_generator/management/commands/generate_views.py
django_generator/templatetags/__init__.py
django_generator/templatetags/to_class_name.py
django_generator/templatetags/utils.py